WindowsContextMenu/__init__.py
WindowsContextMenu/menu_operations.py
WindowsContextMenu/registry_editor.py
WindowsContextMenu/utils.py
WindowsContextMenu-0.1.dist-info/LICENSE
WindowsContextMenu-0.1.dist-info/METADATA
WindowsContextMenu-0.1.dist-info/WHEEL
WindowsContextMenu-0.1.dist-info/top_level.txt
WindowsContextMenu-0.1.dist-info/RECORD
